python_spell/__init__.py
python_spell/checker.py
python_spell/languages/code.txt
python_spell/languages/english.txt
python_spell/languages/french.txt
python_spell/languages/german.txt
python_spell/languages/italian.txt
python_spell/languages/spanish.txt
python_spell/src/__init__.py
python_spell/src/binarytree.py
python_spell/src/hashtable.py
python_spell/src/linkedlist.py
python_spell_checker-1.1.0.dist-info/METADATA
python_spell_checker-1.1.0.dist-info/WHEEL
python_spell_checker-1.1.0.dist-info/licenses/LICENSE
python_spell_checker-1.1.0.dist-info/RECORD
