Metadata-Version: 2.1
Name: python-spell-checker
Version: 1.1.0
Summary: Python spell checker library; supports English, German, Italian, Spanish, French, and even Code!
Project-URL: Homepage, https://github.com/dev0cloo/python-spell-checker
Project-URL: Repository, https://github.com/dev0cloo/python-spell-checker
Author-email: dev0cloo <etor.ocloo@gmail.com>, Harvard90873 <harvard90873@gmail.com>
Maintainer-email: dev0cloo <etor.ocloo@gmail.com>
License: Copyright (c) 2021 Harvard90873
License-File: LICENSE
Keywords: spell-check,spellchecker,typos
Classifier: License :: OSI Approved :: MIT License
Classifier: Operating System :: OS Independent
Classifier: Programming Language :: Python :: 3
Requires-Python: >=3.9
